pyproject.toml
seis_realtime/__init__.py
seis_realtime/config/__init__.py
seis_realtime/config/main.py
seis_realtime/tests/__init__.py
seis_realtime/tests/test_config/__init__.py
seis_realtime/tests/test_config/test_main.py
seis_realtime-0.0.2.dist-info/LICENSE
seis_realtime-0.0.2.dist-info/METADATA
seis_realtime-0.0.2.dist-info/WHEEL
seis_realtime-0.0.2.dist-info/RECORD
